knowledge_pp/__init__.py
knowledge_pp/coltex.py
knowledge_pp/coltypes.py
knowledge_pp/evaluator.py
knowledge_pp/latex.py
knowledge_pp/parser.py
knowledge_pp/parsutils.py
knowledge_pp/scripts/__init__.py
knowledge_pp/scripts/app.py
knowledge_pp-0.0.1.dist-info/LICENSE
knowledge_pp-0.0.1.dist-info/METADATA
knowledge_pp-0.0.1.dist-info/WHEEL
knowledge_pp-0.0.1.dist-info/entry_points.txt
knowledge_pp-0.0.1.dist-info/top_level.txt
knowledge_pp-0.0.1.dist-info/RECORD
