Metadata-Version: 2.1
Name: knowledge-pp
Version: 0.0.1
Summary: Templating Language for Knowledge and LaTeX
Home-page: https://github.com/AliaumeL/knowledge-pp
Author: Aliaume Lopez
Author-email: alopez@irif.fr
License: UNKNOWN
Project-URL: Bug Tracker, https://github.com/AliaumeL/knowledge-pp/issues
Keywords: knowledge :: latex :: pre-processor
Platform: UNKNOWN
Classifier: Programming Language :: Python :: 3
Classifier: License :: OSI Approved :: GNU General Public License v3 (GPLv3)
Classifier: Operating System :: OS Independent
Requires-Python: >=3.6
License-File: LICENSE
Requires-Dist: click
Requires-Dist: dataclasses
